README.rst
setup.py
wrest/__init__.py
wrest.egg-info/PKG-INFO
wrest.egg-info/SOURCES.txt
wrest.egg-info/dependency_links.txt
wrest.egg-info/top_level.txt