Metadata-Version: 1.0
Name: wrest
Version: 0.1.3
Summary: Thin rest client with no dependencies
Home-page: https://github.com/kadirpekel/wrest
Author: Kadir Pekel
Author-email: kadirpekel@gmail.com
License: UNKNOWN
Platform: UNKNOWN
